.coveragerc
.editorconfig
CHANGES.rst
CONTRIBUTORS.rst
MANIFEST.in
README.rst
bootstrap-buildout.py
buildout.cfg
setup.py
travis.cfg
docs/LICENSE.GPL
docs/LICENSE.rst
src/collective/__init__.py
src/collective.fixorderedfolder.egg-info/PKG-INFO
src/collective.fixorderedfolder.egg-info/SOURCES.txt
src/collective.fixorderedfolder.egg-info/dependency_links.txt
src/collective.fixorderedfolder.egg-info/namespace_packages.txt
src/collective.fixorderedfolder.egg-info/not-zip-safe
src/collective.fixorderedfolder.egg-info/requires.txt
src/collective.fixorderedfolder.egg-info/top_level.txt
src/collective/fixorderedfolder/__init__.py
src/collective/fixorderedfolder/configure.zcml
src/collective/fixorderedfolder/testing.py
src/collective/fixorderedfolder/testing.zcml
src/collective/fixorderedfolder/browser/__init__.py
src/collective/fixorderedfolder/browser/configure.zcml
src/collective/fixorderedfolder/browser/view.py
src/collective/fixorderedfolder/tests/__init__.py
src/collective/fixorderedfolder/tests/test_broken_fixed.py