Metadata-Version: 1.1
Name: collective.fixorderedfolder
Version: 0.1a2
Summary: Fix internal data structures of Plone ordered folders
Home-page: http://pypi.python.org/pypi/collective.fixorderedfolder
Author: Godefroid Chapelle
Author-email: gotcha@bubblenet.be
License: GPL
Keywords: Python Plone
Platform: UNKNOWN
Classifier: Environment :: Web Environment
Classifier: Framework :: Plone
Classifier: Framework :: Plone :: 4.3
Classifier: Programming Language :: Python
Classifier: Programming Language :: Python :: 2.7
